{
  "name": "Ethel Hudson",
  "age": 24,
  "address": {
    "street": "Zulo Parkway",
    "city": "Kigiru",
    "state": "KY",
    "zip": "52221"
  },
  "contact": {
    "phone": "(316) 745-8246",
    "servicePhone": "800151377"
  },
  "birthday": "1978-12-29T01:52:37.420Z",
  "ip": "245.147.106.223",
  "foo": "bar",
  "profile": {
    "about": "Tatdu wa noj biofa dupow ve vanbe pab ziit touh ofesi kis. Nic so mi ronodam ki ebdarew gisib capdoksaw pu hol fu zekkees gevlozdu. Far la jibmoh men pecfi ujtese boudlu sek zu gufnawaz hok tewnema. Pofa pimiwkeh lutok ep milvezriz ubpo govi hetmu mar ralca bo izad viledub lezwuw lokvirij bed baofe ihutew.",
    "bio": "Fu col bubkaeb to ruroh bichet ijol zolfa deketoz if uki lesu. Natede ozi ji wi kujev nesi umra fuko bo ze zuosa afmo efipeko kufomif utamez. Zor sijware rug uraba ma vice sovsol jok ofa eg kavmev ivukodrop viomeop wokbauh gem vuh."
  },
  "apiKey": "860b1b7a0f3a987715bd9635607982c884a5e9171accffee77e385715282f2ef",
  "currency": {
    "code": "ZWD",
    "name": "Zimbabwe Dollar"
  }
}