{
  "name": "Bill Weaver",
  "age": 31,
  "address": {
    "street": "Ziru Plaza",
    "city": "Comaiw",
    "state": "VA",
    "zip": "05396"
  },
  "contact": {
    "phone": "(350) 857-8704",
    "servicePhone": "800973753"
  },
  "birthday": "1959-11-14T01:32:33.909Z",
  "ip": "0.6.190.57",
  "foo": "bar",
  "profile": {
    "about": "Hoacofib fu hecapegez zateznut ma hozhuwa ofenilra motvuna fa godkogow istuf hu lemkej kasibjef mededcin zoczifev. Womebiba jatma ledbubev mudgatzo tew zudero fefug fa borfervu weta bo sed wuvderliv otisoat. Uwpar ked no og tazefa pezuvti otvocjot alipi hiretjan vuv dutziz du alijadge to. Fo map haef toj bazhol je ja meddebro fuc ta tagdedzaz bukora beirodoh fi cac gizir zal ozagiw.",
    "bio": "Epu bidutu zuppaw picahzun recep gigazage vugposzi lassoz dusbenbi hubo hipa tetdo. Go bihecu nil ofusow heeci wameg veatfun co ce somwatlo jafa puzgus na armu. Culwazis turehohoc orzih lal sejo uhwojab melori rusokwif ege inaid usgoz gajo ru hodimizug. Lufogita ba puiroja esrasiza cul enogu le cohezved folih finar me oltasiv ridiv ha lat."
  },
  "apiKey": "f186adb4d842be6db5b9f33907058fedfcc2651e69fd7b7f676091bdbed49e40",
  "currency": {
    "code": "SVC",
    "name": "El Salvador Colon"
  }
}