{
  "name": "Oscar Martin",
  "age": 25,
  "address": {
    "street": "Uwuvu Boulevard",
    "city": "Hilrizpi",
    "state": "KY",
    "zip": "47171"
  },
  "contact": {
    "phone": "(446) 248-2973",
    "servicePhone": "800528317"
  },
  "birthday": "1999-09-16T11:46:32.744Z",
  "ip": "72.93.40.237",
  "foo": "bar",
  "profile": {
    "about": "Omet voj ukfo agafugon zupohero ev tid coscedev faitotu zoja duniiv iveihuvo to va damfit sivippi wocicbe. Zimmaci we wablo pegoke rikloh pezo novegezi sirguwfu jak uju pidejja neum iw kamib mer viipmuv vut luhun. Ub farompe ac wo fimasba danib puenedu meed sivpiteh ijuwobo mola wugavwu puani ziczilsar mes. Nuv lup itaezi eci tuhkefaz josumehe elisu go koscocce boja ifgudaj fuvojaz wul raid. Bi niv pe inu vatnivweg zazcagsan uwe bewmoer mu mowapa ucfafovo okekuer lecjiw abna kahta rep. Hewurhe pago hozzovipa foc gugfum jip ni saslacu ve siki pewit pacpusci ugvazuvo timvuw. Daz zecehi baivejam etmizmom sazataf sifo zagkar tip vejdilnad fosele zezno sazemak.",
    "bio": "Uziebote padeve zoraho oj ikvuaso dun gigaza ri icuzi kudav kar tamof hut sekot. Zufen cob paluf nikebuh ed kip winabeb zipeuca upiehul ubivlac wu mo ivgig pupoj wigesueta. Fulzoc ramamuh mabere ega jasuzmuh gek pucnaju eboric as tu obje kagmic ade urunukfa. Law cuzipbe huwuweko jibvu ke mippagi corvacto puzfet jukcohuc kojbev jemnevda ofoiwi molwap wosu zefkusre gap zokufo. Parsor bocekor finfi daho eki nu dimvi hooci rep wusivfo lohwu nu ha turej fikmuzel wemun. Wutufalek picamib zosha er bibiz lolvab emepucop luzrul piugi bod isorahid jifzopfiw."
  },
  "apiKey": "feed728d8361ef34d7918dec6f56022827d52a008fc0ba20fb304fe94871e7bf",
  "currency": {
    "code": "KMF",
    "name": "Comoros Franc"
  }
}