{
  "name": "Lina Garcia",
  "age": 61,
  "address": {
    "street": "Hata Place",
    "city": "Melgafpe",
    "state": "NM",
    "zip": "87790"
  },
  "contact": {
    "phone": "(652) 299-9333",
    "servicePhone": "800779961"
  },
  "birthday": "1987-12-09T10:44:08.230Z",
  "ip": "76.82.185.48",
  "foo": "bar",
  "profile": {
    "about": "Pon suinita pucoktud sajbelu pihi neodso ubiesgig cucin ubarut musgip rov doz. Ro kommopgep okitezme wacudo bokti lajti hostoak suer ja wus bugliz zujopjev lebuh. Howoched iv mosimuh zep alate nohriw duehelov wase huc zok pazhohze hob.",
    "bio": "Beepdub lajih simuhe fasupge jod me have eziwiup lulle oz res mivewal lefud wiwawzew todumukis wuhmah deksencis. Remni gecu etu wod kuar ucavalheh guceh farah ufufe unu na iketusij dij avipauro dukvu. Wogzebo ze hulumais wowge si unalid kozare fujocer mihfagene cuhub bocu huw ne cem ve aldeb jimahi vi. Hujla ciawa labso duczabmar mecizoji acazado fojuiju rom keunadi igu tiiz dalol zecji il nod. Dabuj jize jupavjir kum jaweih utuacoruf lob bud ji buf kiunge si. Safi fam az boboj gavelsal obizajas pilo logare lumauc hu ru ofufovwub fi naktofda pupbuna."
  },
  "apiKey": "b39b683457efc24e2fc6bae97fe884d2c6eb8dfd1bbe3f1372cfc75a99dcfd2d",
  "currency": {
    "code": "TJS",
    "name": "Tajikistan Somoni"
  }
}